{
    "name": "Jyotishankar Patra",
    "location": "Balasore, Odisha, India",
    "bio": "inspiring Student seeking knowledge | Full stack Developer",
    "avatar": "https://avatars.githubusercontent.com/u/119054072?v=4",
    "portfolio": "https://suvam.qwikish.com",
    "skills": [
        "JavaScript",
        "ReactJS",
        "NextJS",
        "ExpressJS",
        "NodeJS",
        "Redux",
        "Tailwind",
        "SQL",
        "PostgreSQL",
        "MongoDB",
        "TypeScript",
        "AWS",
        "Git",
        "Docker",
        "Redis",
        "Kafka"
    ],
    "social": {
        "GitHub": "https://github.com/jyotishankar04",
        "Twitter": "https://x.com/devsuvam1",
        "LinkedIn": "https://www.linkedin.com/in/jyotishankar-patra"
    }
}